README.md
setup.cfg
setup.py
patreon/__init__.py
patreon/api.py
patreon/api_spec.py
patreon/oauth.py
patreon/oauth_spec.py
patreon.egg-info/PKG-INFO
patreon.egg-info/SOURCES.txt
patreon.egg-info/dependency_links.txt
patreon.egg-info/requires.txt
patreon.egg-info/top_level.txt
patreon.egg-info/zip-safe
patreon/jsonapi/__init__.py
patreon/jsonapi/parser.py
patreon/jsonapi/parser_spec.py
patreon/jsonapi/url_util.py
patreon/jsonapi/url_util_spec.py
patreon/schemas/__init__.py
patreon/schemas/campaign.py
patreon/schemas/campaign_spec.py
patreon/schemas/goal.py
patreon/schemas/goal_spec.py
patreon/schemas/pledge.py
patreon/schemas/pledge_spec.py
patreon/schemas/reward.py
patreon/schemas/reward_spec.py
patreon/schemas/user.py
patreon/schemas/user_spec.py
patreon/version_compatibility/__init__.py
patreon/version_compatibility/urllib_parse.py
patreon/version_compatibility/utc_timezone.py
patreon/version_compatibility/utc_timezone_spec.py